py_pcapplusplus-1.0.11.dist-info/RECORD
py_pcapplusplus-1.0.11.dist-info/WHEEL
py_pcapplusplus-1.0.11.dist-info/METADATA
py_pcapplusplus/py_pcapplusplus_ext.abi3.so
py_pcapplusplus/__init__.py
py_pcapplusplus/py.typed
py_pcapplusplus/py_pcapplusplus_ext.pyi
