Metadata-Version: 2.1
Name: py-pcapplusplus
Version: 1.0.11
Summary: Python wrapper module for the Pcap++ library using nanobind
Author-Email: Cymotive <clarity@cymotive.com>
Classifier: License :: OSI Approved :: MIT License
Requires-Python: >=3.10
